easylaser/__init__.py
easylaser/align.py
easylaser/get_model.py
easylaser/laser.py
easylaser/embed/embed.py
easylaser/embed/encoder.py
easylaser/embed/laserLstmEncoder.py
easylaser/embed/laserTransformerEncoder.py
easylaser/embed/multiGpuEncoder.py
easylaser/lib/__init__.py
easylaser/lib/constants.py
easylaser/lib/text_processing.py
easylaser-0.1.5.dist-info/METADATA
easylaser-0.1.5.dist-info/WHEEL
easylaser-0.1.5.dist-info/licenses/LICENSE
easylaser-0.1.5.dist-info/RECORD
