Metadata-Version: 2.1
Name: easylaser
Version: 0.1.5
Summary: An easy to use interface to LASER
Author-email: Lingua Custodia <it@linguacustodia.com>
License-File: LICENSE
Classifier: Development Status :: 4 - Beta
Classifier: License :: OSI Approved :: BSD License
Classifier: Operating System :: OS Independent
Classifier: Programming Language :: Python :: 3.10
Requires-Python: >=3.7
Requires-Dist: fairseq
Requires-Dist: faiss-cpu
Requires-Dist: ftfy
Requires-Dist: requests
Requires-Dist: sentencepiece
